geodataflow/pipelineapi.default.settings
geodataflow/pipelineapi.py
geodataflow/api/__init__.py
geodataflow/api/__meta__.py
geodataflow/api/database.py
geodataflow/api/models.py
geodataflow/api/schema.py
geodataflow.api-0.2.1.dist-info/LICENSE
geodataflow.api-0.2.1.dist-info/METADATA
geodataflow.api-0.2.1.dist-info/WHEEL
geodataflow.api-0.2.1.dist-info/dependency_links.txt
geodataflow.api-0.2.1.dist-info/top_level.txt
geodataflow.api-0.2.1.dist-info/RECORD
