Metadata-Version: 2.1
Name: geodataflow.api
Version: 0.2.1
Summary: REST WebAPI for GeodataFlow, one Geoprocessing framework for geographical & Earth Observation (EO) data.
Home-page: https://github.com/ahuarte47/geodataflow
Author: Alvaro Huarte
Author-email: ahuarte47@gmail.com
License: Apache 2.0
Project-URL: Bug Tracker, https://github.com/ahuarte47/geodataflow/issues/
Project-URL: Source Code, https://github.com/ahuarte47/geodataflow
Classifier: Development Status :: 2 - Pre-Alpha
Classifier: Intended Audience :: Developers
Classifier: Intended Audience :: Education
Classifier: Intended Audience :: Information Technology
Classifier: Intended Audience :: Science/Research
Classifier: Natural Language :: English
Classifier: License :: OSI Approved :: Apache Software License
Classifier: Operating System :: OS Independent
Classifier: Programming Language :: Python
Classifier: Programming Language :: Python :: 3
Classifier: Programming Language :: Python :: 3.7
Classifier: Programming Language :: Python :: 3.8
Classifier: Programming Language :: Python :: 3.9
Classifier: Programming Language :: Python :: 3.10
Classifier: Topic :: Scientific/Engineering :: Atmospheric Science
Classifier: Topic :: Scientific/Engineering :: Information Analysis
Classifier: Topic :: Scientific/Engineering :: GIS
Classifier: Topic :: Scientific/Engineering :: Image Processing
Classifier: Topic :: Software Development :: Libraries :: Application Frameworks
Classifier: Topic :: Software Development :: Libraries :: Python Modules
Requires-Python: >=3.7
License-File: LICENSE
Requires-Dist: geodataflow.core
Requires-Dist: pydantic
Requires-Dist: SQLAlchemy
Requires-Dist: aiopg
Requires-Dist: aiosqlite
Requires-Dist: fastapi
Requires-Dist: uvicorn
Provides-Extra: dataframes
Requires-Dist: geodataflow.dataframes ; extra == 'dataframes'
Provides-Extra: eodag
Requires-Dist: eodag (>=2.4.0) ; extra == 'eodag'
Provides-Extra: gee
Requires-Dist: earthengine-api (==0.1.320) ; extra == 'gee'
Provides-Extra: spatial
Requires-Dist: geodataflow.spatial ; extra == 'spatial'
